microcorex/__init__.py
microcorex/app_service.py
microcorex/base_grpc_client.py
microcorex/config.py
microcorex/config_loader.py
microcorex/grpc_client.py
microcorex/grpc_decorators.py
microcorex/grpc_server.py
microcorex/logging_setup.py
microcorex/nacos_config_manager.py
microcorex/nacos_registrar.py
microcorex/service_registry.py
microcorex/utils.py
microcorex-0.0.1.dist-info/licenses/LICENSE
microcorex-0.0.1.dist-info/METADATA
microcorex-0.0.1.dist-info/WHEEL
microcorex-0.0.1.dist-info/top_level.txt
microcorex-0.0.1.dist-info/RECORD
