Metadata-Version: 2.4
Name: microcorex
Version: 0.0.1
Summary: Python microservices framework core library providing configuration management, service lifecycle, gRPC support and more
Author-email: xiaoke <codexiaoke@126.com>
License: MIT
Project-URL: Homepage, https://github.com/codexiaoke/microcorex
Project-URL: Documentation, https://github.com/codexiaoke/microcorex/blob/master/README.md
Project-URL: Repository, https://github.com/codexiaoke/microcorex
Keywords: microcorex,grpc,fastapi,nacos,configuration
Classifier: Development Status :: 3 - Alpha
Classifier: Intended Audience :: Developers
Classifier: License :: OSI Approved :: MIT License
Classifier: Programming Language :: Python :: 3
Classifier: Programming Language :: Python :: 3.8
Classifier: Programming Language :: Python :: 3.9
Classifier: Programming Language :: Python :: 3.10
Classifier: Programming Language :: Python :: 3.11
Requires-Python: >=3.8
License-File: LICENSE
Requires-Dist: PyYAML==6.0.3
Requires-Dist: fastapi==0.121.0
Requires-Dist: uvicorn==0.38.0
Requires-Dist: pydantic==2.12.4
Requires-Dist: nacos-sdk-python==2.0.9
Requires-Dist: grpcio==1.76.0
Requires-Dist: grpcio-tools==1.76.0
Requires-Dist: pydantic-settings==2.11.0
Requires-Dist: loguru==0.7.3
Provides-Extra: dev
Requires-Dist: pytest>=7.0.0; extra == "dev"
Requires-Dist: pytest-asyncio>=0.21.0; extra == "dev"
Requires-Dist: black>=23.0.0; extra == "dev"
Requires-Dist: flake8>=6.0.0; extra == "dev"
Dynamic: license-file
